MetaStalk/__init__.py
MetaStalk/main.py
MetaStalk/modules/DateTime.py
MetaStalk/modules/GPSCheck.py
MetaStalk/modules/PieChart.py
MetaStalk/modules/Stats.py
MetaStalk/modules/__init__.py
MetaStalk/utils/__init__.py
MetaStalk/utils/export.py
MetaStalk/utils/logger.py
MetaStalk/utils/parse.py
MetaStalk/utils/update.py
MetaStalk/utils/web.py
MetaStalk/utils/assets/favicon.ico
MetaStalk-2.2.2.dist-info/LICENSE
MetaStalk-2.2.2.dist-info/METADATA
MetaStalk-2.2.2.dist-info/WHEEL
MetaStalk-2.2.2.dist-info/entry_points.txt
MetaStalk-2.2.2.dist-info/top_level.txt
MetaStalk-2.2.2.dist-info/RECORD
