Metadata-Version: 2.1
Name: MetaStalk
Version: 2.2.2
Summary: Metadata analyzer and visualizer
Home-page: https://gitlab.com/Cyb3r-Jak3/MetaStalk
Author: Cyb3r Jak3
Author-email: jake@jwhite.network
License: MPL 2.0
Download-URL: https://gitlab.com/Cyb3r-Jak3/metastalk/-/releases
Project-URL: Issues, https://gitlab.com/Cyb3r-Jak3/MetaStalk/issues
Project-URL: Source, https://gitlab.com/Cyb3r-Jak3/MetaStalk/-/tree/master
Project-URL: CI, https://gitlab.com/Cyb3r-Jak3/MetaStalk/pipelines
Project-URL: Releases, https://github.com/Cyb3r-Jak3/MetaStalk/releases
Keywords: exif image metadata photo plotly dash heic
Platform: any
Classifier: License :: OSI Approved :: Mozilla Public License 2.0 (MPL 2.0)
Classifier: Operating System :: OS Independent
Classifier: Natural Language :: English
Classifier: Programming Language :: Python :: 3.6
Classifier: Programming Language :: Python :: 3.7
Classifier: Programming Language :: Python :: 3.8
Classifier: Development Status :: 5 - Production/Stable
Classifier: Environment :: Console
Classifier: Topic :: Scientific/Engineering :: Information Analysis
Classifier: Topic :: Utilities
Requires-Python: >=3.6
Requires-Dist: exifreader (==0.1.1)
Requires-Dist: plotly (==4.8.2)
Requires-Dist: pandas (==1.0.5)
Requires-Dist: dash (==1.13.4)
Requires-Dist: requests (==2.24.0)
Provides-Extra: all
Requires-Dist: black (==19.10b0) ; extra == 'all'
Requires-Dist: bandit (==1.6.2) ; extra == 'all'
Requires-Dist: pylint (==2.5.0) ; extra == 'all'
Requires-Dist: flake8 (==3.7.9) ; extra == 'all'
Requires-Dist: coverage (==4.5.4) ; extra == 'all'
Requires-Dist: tox (==3.15.2) ; extra == 'all'
Requires-Dist: psutil (==5.7.0) ; extra == 'all'
Provides-Extra: dev
Requires-Dist: black (==19.10b0) ; extra == 'dev'
Requires-Dist: bandit (==1.6.2) ; extra == 'dev'
Requires-Dist: pylint (==2.5.3) ; extra == 'dev'
Requires-Dist: flake8 (==3.8.3) ; extra == 'dev'
Requires-Dist: coverage (==5.2) ; extra == 'dev'
Requires-Dist: tox (==3.16.1) ; extra == 'dev'
Provides-Extra: image
Requires-Dist: psutil (==5.7.0) ; extra == 'image'
